Workbook

Sheet Rateio LFT
A1: Account | B1: Data de Compra | C1: Investido (BRL) | D1: IOF (BRL) | E1: IR (BRL) | F1: Rendimento Bruto (BRL) | G1: Rendimento Líquido (BRL) | H1: Lucro Bruto % | I1: Lucro Líquido % | J1: e-mail | K1: name
A2: 6pgtAbfCwukveUfKYm22FEHP8w7NKD9Vd73NaCExLAKi | B2: 46045 | C2: 59773.07 | D2: 146.68 | E2: 43.75 | F2: 341.12 | G2: 150.69 | H2: 0.0057069178 | I2: 0.002521035 | J2: =VLOOKUP(A2,Sheet1!A$1:Z$18,3) -> stephane@prosperojus.com.br | K2: =VLOOKUP(A2,Sheet1!A$1:AA$18,11,FALSE) -> Stephane Alberto Lopes
A3: CbVUNS2kgnJszuWwP7ioxGLkUHGWppbcAitC5AynnDSx | B3: 46045 | C3: 59773.07 | D3: 146.68 | E3: 43.75 | F3: 341.12 | G3: 150.69 | H3: 0.0057069178 | I3: 0.002521035 | J3: =VLOOKUP(A3,Sheet1!A$1:Z$18,3,) -> ivan.yuri31@gmail.com | K3: =VLOOKUP(A3,Sheet1!A$1:AA$18,11,FALSE) -> Ivan Augusto Yuri Rodarte
A4: czTNJnh5ihaYfaWzSjjratZrqMcw318KAPBQHdsvVBf | B4: 46045 | C4: 29886.53 | D4: 73.34 | E4: 21.88 | F4: 170.56 | G4: 75.34 | H4: 0.0057069188 | I4: 0.0025208681 | J4: =VLOOKUP(A4,Sheet1!A$1:Z$18,3,) -> marcelo@mbsadv.com | K4: =VLOOKUP(A4,Sheet1!A$1:AA$18,11,FALSE) -> Marcelo Godoy da Cunha Magalhaes
A5: Ai6gzjwzCL9E1rVMR9gP5gD9Y9Eds1uKj1NoC3ggJw4T | B5: 46045 | C5: 29886.53 | D5: 73.34 | E5: 21.88 | F5: 170.56 | G5: 75.34 | H5: 0.0057069188 | I5: 0.0025208681 | J5: =VLOOKUP(A5,Sheet1!A$1:Z$18,3,) -> claytoncampos76@gmail.com | K5: =VLOOKUP(A5,Sheet1!A$1:AA$18,11,FALSE) -> Clayton de Camargo Campos
A6: 9bxQUSioYmCfqeraQ4x1UND5k2PLMmMxLDMCGxVW9Mzz | B6: 46045 | C6: 29886.54 | D6: 73.34 | E6: 21.88 | F6: 170.56 | G6: 75.34 | H6: 0.0057069169 | I6: 0.0025208673 | J6: =VLOOKUP(A6,Sheet1!A$1:Z$18,3,) -> palmier@qmscapital.com.br | K6: =VLOOKUP(A6,Sheet1!A$1:AA$18,11,FALSE) -> Andre Luiz da Fonseca Palmier Nunes
A7: 8wju6VrZpjoZC5TZTGWVJSjNMnz8qeKweZpArcu8BoX9 | B7: 46045 | C7: 29886.54 | D7: 73.34 | E7: 21.88 | F7: 170.56 | G7: 75.34 | H7: 0.0057069169 | I7: 0.0025208673 | J7: =VLOOKUP(A7,Sheet1!A$1:Z$18,3,) -> albitaly360@gmail.com | K7: =VLOOKUP(A7,Sheet1!A$1:AA$18,11,FALSE) -> Nanci Szechtman Bannwart
A8: 3qsNsvWUJsZTk9FS3mmFv2YiUD6gPUJwpeqLQv4ahof8 | B8: 46045 | C8: 29886.54 | D8: 73.34 | E8: 21.87 | F8: 170.56 | G8: 75.34 | H8: 0.0057069169 | I8: 0.0025208673 | J8: =VLOOKUP(A8,Sheet1!A$1:Z$18,3,) -> #N/A | K8: =VLOOKUP(A8,Sheet1!A$1:AA$18,11,FALSE) -> #N/A
A9: 3hJgnmP5gZfkV876PnvJpzCUrq9vGm9fckQNhUB6ftWV | B9: 46045 | C9: 29886.54 | D9: 73.34 | E9: 21.87 | F9: 170.56 | G9: 75.35 | H9: 0.0057069169 | I9: 0.0025212019 | J9: =VLOOKUP(A9,Sheet1!A$1:Z$18,3,) -> #N/A | K9: =VLOOKUP(A9,Sheet1!A$1:AA$18,11,FALSE) -> #N/A
A10: 5h1sZWC93q9mWihsa2tvrsuJoqGY58655CSHkug2opRV | B10: 46045 | C10: 29886.54 | D10: 73.34 | E10: 21.87 | F10: 170.56 | G10: 75.35 | H10: 0.0057069169 | I10: 0.0025212019 | J10: =VLOOKUP(A10,Sheet1!A$1:Z$18,3,) -> pedromarinhonunes63@gmail.com | K10: =VLOOKUP(A10,Sheet1!A$1:AA$18,11,FALSE) -> Pedro Rezende Marinho Nunes
A11: GMuR2i1TfXKvdXJn3iBZCdXomnqVQN3NpEApnmixEndb | B11: 46045 | C11: 29886.54 | D11: 73.34 | E11: 21.87 | F11: 170.56 | G11: 75.35 | H11: 0.0057069169 | I11: 0.0025212019 | J11: =VLOOKUP(A11,Sheet1!A$1:Z$18,3,) -> dhcohn18@gmail.com | K11: =VLOOKUP(A11,Sheet1!A$1:AA$18,11,FALSE) -> Daniel Henrique Cohn
A12: 3DHW2ZCYcKdzqBxyeVcG6TxG6foHdokvJS6Xr55VKPZq | B12: 46045 | C12: 29886.54 | D12: 73.34 | E12: 21.87 | F12: 170.56 | G12: 75.35 | H12: 0.0057069169 | I12: 0.0025212019 | J12: =VLOOKUP(A12,Sheet1!A$1:Z$18,3,) -> ygormunhoz1@gmail.com | K12: =VLOOKUP(A12,Sheet1!A$1:AA$18,11,FALSE) -> Ygor Bernardo Munhoz
A13: 5C7R3fhGJ37wBWEbSrw8KU8sfj8zeoctDAFDkLxcJmgv | B13: 46045 | C13: 29886.54 | D13: 73.34 | E13: 21.87 | F13: 170.56 | G13: 75.35 | H13: 0.0057069169 | I13: 0.0025212019 | J13: =VLOOKUP(A13,Sheet1!A$1:Z$18,3,) -> maurobergstein@gmail.com | K13: =VLOOKUP(A13,Sheet1!A$1:AA$18,11,FALSE) -> Mauro Bergstein
A14: GuU4YH1v6DdkbZwh5Qi7prDxEupGFTtUaTU7EpzRHbQU | B14: 46045 | C14: 1245.27 | D14: 3.06 | E14: 0.91 | F14: 7.1 | G14: 3.14 | H14: 0.0057015748 | I14: 0.0025215415 | J14: =VLOOKUP(A14,Sheet1!A$1:Z$18,3,) -> #N/A | K14: =VLOOKUP(A14,Sheet1!A$1:AA$18,11,FALSE) -> #N/A
A15: AiYxij88KRXxWiAhNMqzxBd33wu5CSUd6KPAdoZETgfL | B15: 46052 | C15: 256148.18 | D15: 496.89 | E15: 57.6 | F15: 752.87 | G15: 198.38 | H15: 0.0029391971 | I15: 0.00077447359 | J15: =VLOOKUP(A15,Sheet1!A$1:Z$18,3,) -> alexandreacp@gmail.com | K15: Delfos

Sheet Sheet1
A1: Carteira de Destino (Wallet) | B1: Carimbo de data/hora | C1: Endereço de e-mail | D1: Termo de Consentimento e Responsabilidade | E1: Qual é a natureza da conta a ser aberta? | F1: Razão Social (Conforme registrado no Contrato Social/Estatuto) | G1: CNPJ (Cadastro Nacional da Pessoa Jurídica) | H1: Identificação de Sócios e Beneficiários Finais (UBO) | I1: Upload: Atos Constitutivos | J1: Upload: Documentos dos Sócios/Administradores | K1: Nome Completo | L1: CPF (Cadastro de Pessoas Físicas) | M1: Data de Nascimento | N1: Nacionalidade | O1: Endereço Residencial | P1: Upload: Documento de Identificação | Q1: Upload: Comprovante de Residência | R1: Renda Mensal (PF) ou Faturamento Médio Mensal (PJ) | S1: Volume Mensal Estimado de Transações na Skatt | T1: Declaração de Pessoa Politicamente Exposta (PPE) | U1: Dados Bancários Principal - Conta de Origem | V1: Carteira de Destino (Wallet) | W1: Nível de Conhecimento em Criptoativos | X1: Objetivo da Conta | Y1: Depositou? | Z1: Contrato Enviado
A2: 6pgtAbfCwukveUfKYm22FEHP8w7NKD9Vd73NaCExLAKi | B2: 46042.494 | C2: stephane@prosperojus.com.br | D2: Sim, concordo e autorizo o tratamento dos meus dados | E2: Pessoa Física (PF) | K2: Stephane Alberto Lopes | L2: 23447327804 | M2: 27953 | N2: Francesa | O2: Rua Seridó, 106, 261-B, Jardim Europa, São Paulo, São Paulo, 01455-040 | P2: https://drive.google.com/open?id=1EXBtJbp1ToG21SdUVkLOxTGPgh0cI_S6 | Q2: https://drive.google.com/open?id=1W_j7gztfEm4D8Es7WH9sm8XEZrOoAINW | R2: 350000 | S2: 60000 | T2: Não | U2: Itau, conta corrente, 3777, 16003-1 | V2: 6pgtAbfCwukveUfKYm22FEHP8w7NKD9Vd73NaCExLAKi | W2: Intermediário (Já realizei operações, mas não conheço detalhes técnicos) | X2: Investimento de Longo Prazo (Hold) | Y2: SIM | Z2: SIM
A3: 8wju6VrZpjoZC5TZTGWVJSjNMnz8qeKweZpArcu8BoX9 | B3: 46042.685 | C3: albitaly360@gmail.com | D3: Sim, concordo e autorizo o tratamento dos meus dados | E3: Pessoa Física (PF) | K3: Nanci Szechtman Bannwart | L3: 25481857880 | M3: 27169 | N3: Brasileira | O3: Alameda barros 7”2, apto 151, cep 01232-000 SP/SP | P3: https://drive.google.com/drive/u/1/folders/14g3smzR0068eovWdd1B5-Ft03qsUUQqnucdazEz6KXFUqFqVe2lRxgZ49ON9rFvZi9iBrgnd | Q3: https://drive.google.com/open?id=1nI1A3D4f56lflc7z2cc5vUhWkEbkbrXE | R3: 150000 | S3: 50000 | T3: Não | U3: Banco itau 3777 cc 14229-4 | V3: 8wju6VrZpjoZC5TZTGWVJSjNMnz8qeKweZpArcu8BoX9 | W3: Intermediário (Já realizei operações, mas não conheço detalhes técnicos) | X3: Investimento de Longo Prazo (Hold) | Y3: SIM | Z3: SIM
A4: czTNJnh5ihaYfaWzSjjratZrqMcw318KAPBQHdsvVBf | B4: 46042.687 | C4: marcelo@mbsadv.com | D4: Sim, concordo e autorizo o tratamento dos meus dados | E4: Pessoa Física (PF) | K4: Marcelo Godoy da Cunha Magalhaes | L4: 30516176870 | M4: 29987 | N4: Brasileiro | O4: Rua Dr Alberto Lyra 345 Apto 21 | P4: https://drive.google.com/open?id=1BqQHLc8PmYDgwRyJjsW00l2nn-8_T-n0 | Q4: https://drive.google.com/open?id=1mZQj4tYQyal4G51VSq4brohGyF9nSGPS | R4: 150000 | S4: 50000 | T4: Não | U4: Bradesco conta corrente agencia 0133 conta 391236-1 | V4: czTNJnh5ihaYfaWzSjjratZrqMcw318KAPBQHdsvVBf | W4: Básico (Tenho pouco ou nenhum conhecimento) | X4: Investimento de Longo Prazo (Hold) | Y4: SIM | Z4: SIM
A5: CbVUNS2kgnJszuWwP7ioxGLkUHGWppbcAitC5AynnDSx | B5: 46042.689 | C5: ivan.yuri31@gmail.com | D5: Sim, concordo e autorizo o tratamento dos meus dados | E5: Pessoa Física (PF) | K5: Ivan Augusto Yuri Rodarte | L5: 36693487866 | M5: 32608 | N5: Brasileiro | O5: 4532082 | P5: https://drive.google.com/open?id=1T-hJe8uIqiuqIO963t3Ojdxq6PiSFBjE | Q5: https://drive.google.com/open?id=11jEwfU-6wLrFuyjJijuFADkWJCeKnDZJ | R5: 90000 | S5: 30000 | T5: Não | U5: Itaú, conta corrente, 7048, 310000-4, 11976223961 | V5: CbVUNS2kgnJszuWwP7ioxGLkUHGWppbcAitC5AynnDSx | W5: Intermediário (Já realizei operações, mas não conheço detalhes técnicos) | X5: Investimento de Longo Prazo (Hold) | Y5: SIM | Z5: SIM
A6: Ai6gzjwzCL9E1rVMR9gP5gD9Y9Eds1uKj1NoC3ggJw4T | B6: 46043.496 | C6: claytoncampos76@gmail.com | D6: Sim, concordo e autorizo o tratamento dos meus dados | E6: Pessoa Física (PF) | K6: Clayton de Camargo Campos | L6: 25025335892 | M6: 27855 | N6: Brasileira | O6: Rua Fonseca Teixieira, 15, Sao Paulo, SP, CEP 05670-040 | P6: https://drive.google.com/open?id=1u8qfDLZYSe5-5moRZOAz9x-voB6M1yjc | Q6: https://drive.google.com/open?id=1n3zrGugAUb_uXTO771-5j-7qO8UghKZI | R6: 50000 | S6: 20000 | T6: Não | U6: Itau / ag 1608 / conta 29430-0 | V6: Ai6gzjwzCL9E1rVMR9gP5gD9Y9Eds1uKj1NoC3ggJw4T | W6: Intermediário (Já realizei operações, mas não conheço detalhes técnicos) | X6: Investimento de Longo Prazo (Hold) | Y6: SIM | Z6: SIM
B7: 46043.803 | C7: pedromarinhonunes63@gmail.com | D7: Não concordo
A8: 9bxQUSioYmCfqeraQ4x1UND5k2PLMmMxLDMCGxVW9Mzz | B8: 46043.811 | C8: palmier@qmscapital.com.br | D8: Sim, concordo e autorizo o tratamento dos meus dados | E8: Pessoa Física (PF) | K8: Andre Luiz da Fonseca Palmier Nunes | L8: 86356666749 | M8: 24300 | N8: Brasileiro | O8: Av Afonso Braz 155 ap 171 | P8: https://drive.google.com/open?id=1bz5HwewKiaffuqKY2ZCSfRa3z5WcdSff | Q8: https://drive.google.com/open?id=1omWAb2x4x2l244dFc3e4rZEtaTfeo4TL | R8: 200000 | S8: 1 | T8: Não | U8: Banco itau conta corrente agencia 3777 conta 07627-8 | V8: 9bxQUSioYmCfqeraQ4x1UND5k2PLMmMxLDMCGxVW9Mzz | W8: Básico (Tenho pouco ou nenhum conhecimento) | X8: Investimento de Longo Prazo (Hold) | Y8: SIM | Z8: SIM
A9: H9kLXtDvbEf4SULy2qLuAKQje2vo3hNCNvoAwzvTmgue | B9: 46043.816 | C9: skulikovsky@gmail.com | D9: Sim, concordo e autorizo o tratamento dos meus dados | E9: Pessoa Física (PF) | K9: Sergio Kulikovsky | L9: 15156683800 | M9: 25641 | N9: Brasil | O9: 3 Boronia Road, Bellevue Hill NSW 2023 Australia | P9: https://drive.google.com/open?id=1zA-6CqkarGTJlmucKGT1mLHj6EoLTU-v | Q9: https://drive.google.com/open?id=1DvoVGYTuoyyHc4VzY19uLETkupwB95Sl | R9: 100000 | S9: 50000 | T9: Não | U9: Banco 260, Ag 001, CC 3682197-4, chave Pix: kulikovsky@hotmail.com | V9: H9kLXtDvbEf4SULy2qLuAKQje2vo3hNCNvoAwzvTmgue | W9: Avançado (Conheço o funcionamento de blockchain, custódia e volatilidade) | X9: Investimento de Longo Prazo (Hold) | Z9: SIM
A10: GMuR2i1TfXKvdXJn3iBZCdXomnqVQN3NpEApnmixEndb | B10: 46045.432 | C10: dhcohn18@gmail.com | D10: Sim, concordo e autorizo o tratamento dos meus dados | E10: Pessoa Física (PF) | K10: Daniel Henrique Cohn | L10: 15362211803 | M10: 25469 | N10: Brasileira | O10: Rua Angelina Maffei Vita, 344 - Apto 101, Jardim Europa, São Paulo, SP, CEP 01455-070 | P10: https://drive.google.com/open?id=1rR10QYLEqUWyZC34XV60mTIvTdxINKIJ | Q10: https://drive.google.com/open?id=1l55DYfgV1zCawcPf8JF5WcWN_ZWIRmYS | R10: 100000 | S10: 30000 | T10: Não | U10: Itaú, conta corrente, 3777 / 00846-1, 11991542141 | V10: GMuR2i1TfXKvdXJn3iBZCdXomnqVQN3NpEApnmixEndb | W10: Básico (Tenho pouco ou nenhum conhecimento) | X10: Investimento de Longo Prazo (Hold) | Z10: SIM
A11: 7TAi5LCh5BGkH62y8o5F1cbY2jwBqYD946fhTY7JLnXH | B11: 46045.692 | C11: cesar.viana@succespar.com.br | D11: Sim, concordo e autorizo o tratamento dos meus dados | E11: Pessoa Física (PF) | K11: Cesar Augusto Pires Viana | L11: 003.755.399-21 | M11: 28129 | N11: Brasileiro | O11: Av ibirapuera 2332 - 111 T2 - Indianopolis CEP 04028002 | P11: https://drive.google.com/open?id=1-AWrL3yGiECiZNSvsbKKzG4n1F30g962 | Q11: https://drive.google.com/open?id=1nKX92ffki17SLed4HvGAYB-YM5iOQVLC | R11: 140000 | S11: 1 | T11: Não | U11: Banco Itau Ag 7051 C/C 29.643-7 | V11: 7TAi5LCh5BGkH62y8o5F1cbY2jwBqYD946fhTY7JLnXH | W11: Básico (Tenho pouco ou nenhum conhecimento) | X11: Investimento de Longo Prazo (Hold) | Z11: SIM
A12: fgrv6mX2wApQYX3mow7mtRRyJ4qNS5zKnUXCnBGDHQD | B12: 46048.544 | C12: amaral@vintageinvest.com.br | D12: Sim, concordo e autorizo o tratamento dos meus dados | E12: Pessoa Física (PF) | K12: Guilherme Amaral Ferraz | L12: 059.484.968-30 | M12: 23458 | N12: São Paulo | O12: Piazza Giovine Italia 002 - 20123 Milano Mi Italia | P12: https://drive.google.com/open?id=1JB7XfDHgUHfSfXhIzhLIGCJvQl4-c7NH | Q12: https://drive.google.com/open?id=1LhfoE6SvT8HjNcTwiEAyKblWEUC8BqPl | R12: 300000 | S12: 1 | T12: Não | U12: banco BTG Conta INR ( Investidor Nao Residente ) | V12: fgrv6mX2wApQYX3mow7mtRRyJ4qNS5zKnUXCnBGDHQD | W12: Intermediário (Já realizei operações, mas não conheço detalhes técnicos) | X12: Investimento de Longo Prazo (Hold) | Z12: SIM
A13: 5C7R3fhGJ37wBWEbSrw8KU8sfj8zeoctDAFDkLxcJmgv | B13: 46048.925 | C13: maurobergstein@gmail.com | D13: Sim, concordo e autorizo o tratamento dos meus dados | E13: Pessoa Física (PF) | K13: Mauro Bergstein | L13: 92637434791 | M13: 24815 | N13: Brazil | O13: Rua Morás 506/41 | P13: https://drive.google.com/open?id=1coYkb6AmeCb8ICTaXZYKX2pU_sPk1Tu6 | Q13: https://drive.google.com/open?id=1z2JAbbw0yu5cez5QYC63aX1TQKaW9Kjd | R13: 40000 | S13: 5000 | T13: Não | U13: Banco Itaú / agência 3777 c/c 13033-1 / pix: 92637434791 | V13: 5C7R3fhGJ37wBWEbSrw8KU8sfj8zeoctDAFDkLxcJmgv | W13: Básico (Tenho pouco ou nenhum conhecimento) | X13: Investimento de Longo Prazo (Hold) | Z13: SIM
A14: 3VJhVPnbQ8kJsy6shcHPzdySNjEaZQHVKdu8YakrHfwu | B14: 46049.429 | C14: ednammsalles@gmail.com | D14: Sim, concordo e autorizo o tratamento dos meus dados | E14: Pessoa Física (PF) | K14: Rodolfo Henrique Fischer | L14: 83871543853 | M14: 23006 | N14: Brasileira | O14: Rua Recanto, 127 - Chácara Flora - CEP: 04644-020 - São Paulo | P14: https://drive.google.com/open?id=1Saqzr3SAkVJ-3AhN1NYwZzWdHTIDlQnQ | Q14: https://drive.google.com/open?id=1w5Jhk-zyZtAGYQeeVL6ZFEG8sY620v5P | R14: 100000 | S14: Não será movimentada | T14: Não | U14: Banco Itaú - agência 3747 c/c: 00681-9 | V14: 3VJhVPnbQ8kJsy6shcHPzdySNjEaZQHVKdu8YakrHfwu | W14: Avançado (Conheço o funcionamento de blockchain, custódia e volatilidade) | X14: Investimento de Longo Prazo (Hold) | Z14: SIM
A15: 5h1sZWC93q9mWihsa2tvrsuJoqGY58655CSHkug2opRV | B15: 46049.788 | C15: pedromarinhonunes63@gmail.com | D15: Sim, concordo e autorizo o tratamento dos meus dados | E15: Pessoa Física (PF) | K15: Pedro Rezende Marinho Nunes | L15: 89331214715 | M15: 23127 | N15: Brasil | O15: Rua Tucuma 712, 111, SP - SP cep 01455-010 | P15: https://drive.google.com/open?id=1HdXMglKUcldk3BMUMTfLcR4hVo0xEFKs | Q15: https://drive.google.com/open?id=19x8DLvG3T8nW-Ds1jRcTo6FwTGdIofre | R15: 300000 | S15: 20000 | T15: Não | U15: Itau, conta corrente, 3789, 14412-2, 893.312.147-15 (cpf, chave pix) | V15: 5h1sZWC93q9mWihsa2tvrsuJoqGY58655CSHkug2opRV | W15: Avançado (Conheço o funcionamento de blockchain, custódia e volatilidade) | X15: Investimento de Longo Prazo (Hold) | Z15: SIM
A16: 3DHW2ZCYcKdzqBxyeVcG6TxG6foHdokvJS6Xr55VKPZq | B16: 46050.705 | C16: ygormunhoz1@gmail.com | D16: Sim, concordo e autorizo o tratamento dos meus dados | E16: Pessoa Física (PF) | K16: Ygor Bernardo Munhoz | L16: 36866198810 | M16: 31930 | N16: Brasileiro | O16: Rua Macurape, 43, Apto 141, Itaim Bibi, São Paulo, SP, 04537060 | P16: https://drive.google.com/open?id=1bvbEHyrDA75aK62woioXgQtSVIwk99Jk | Q16: https://drive.google.com/open?id=15Rn15QZwnxNanpY-fH21CmHOR5WF2I1P | R16: 300000 | S16: 60000 | T16: Não | U16: Itau, CC, 9073, 24945-1, 11976525949 | V16: 3DHW2ZCYcKdzqBxyeVcG6TxG6foHdokvJS6Xr55VKPZq | W16: Avançado (Conheço o funcionamento de blockchain, custódia e volatilidade) | X16: Investimento de Longo Prazo (Hold) | Z16: SIM
A17: 5GWRWpHSH3VopRfviLSP3kWGF9HL38bvWf5wPR2dKGS8 | B17: 46050.755 | C17: desiree@nox.trading / jp@nox.trading | D17: Sim, concordo e autorizo o tratamento dos meus dados | E17: Pessoa Jurídica (PJ) | F17: NOXPAY.IO PAGAMENTOS LTDA | G17: 57.075.201/0001-75 | H17: JOÃO PAULO DOS SANTOS OLIVEIRA | I17: https://drive.google.com/open?id=1HGtBzxH6dzWuBz6DZ1qNdD1oyhhp6LAu | J17: https://drive.google.com/open?id=1y3VVMHIywx8h_quIcuRunZ6SN70zItta | R17: 300k mês | S17: 1 milhão de reais | T17: Não | U17: CNPJ: 57.075.201/0001-75 Banco Sicoob: 756 Agência/Cooperativa: 4439 Conta: 150.209-3 Tipo: Conta corrente chave pix 29555957-0891-417b-88c7-04eb1d6b04ff | V17: 5GWRWpHSH3VopRfviLSP3kWGF9HL38bvWf5wPR2dKGS8 | W17: Avançado (Conheço o funcionamento de blockchain, custódia e volatilidade) | X17: Pagamentos e Transferências | Z17: SIM
A18: AiYxij88KRXxWiAhNMqzxBd33wu5CSUd6KPAdoZETgfL | B18: 46051.499 | C18: alexandreacp@gmail.com | D18: Sim, concordo e autorizo o tratamento dos meus dados | E18: Pessoa Jurídica (PJ) | F18: RED HILL TRADING LIMITED | G18: 2071773 | H18: Delfos Machado Neto - 100% | I18: https://drive.google.com/open?id=1HZJczsaA7M7dmL-IXV93caTPjfRZisF-, https://drive.google.com/open?id=1MCIMFpavwn-4AIj3_g5yCw4Bd0Egg0Jn, https://drive.google.com/open?id=1edE03xDL-cjpn_3PiMWqe-BVaz6yoRM7 | J18: https://drive.google.com/open?id=15ykWeVu0eQ1F5vc4EUPIzZIxOmZkH6KJ | R18: 350000 | S18: 50,000.00 | T18: Não | U18: Entidade Extrangeira, não possui conta bancária no Brazil. | V18: AiYxij88KRXxWiAhNMqzxBd33wu5CSUd6KPAdoZETgfL | W18: Avançado (Conheço o funcionamento de blockchain, custódia e volatilidade) | X18: Trading / Especulação de Curto Prazo
